[
  {
    "timestamp": "2025-11-03T11:22:28.029419",
    "new_projects_count": 16,
    "new_projects": [
      {
        "Nombre": "Programa Innovación Empresarial",
        "Fuente": "Corfo",
        "Fecha cierre": "2025-12-04",
        "Enlace": "https://www.corfo.cl/programa-innovación-empresarial",
        "Estado": "Abierto",
        "Monto": "USD 15,000,000",
        "Área de interés": "Innovación Tecnológica",
        "Descripción": "Apoyo a empresas innovadoras en el sector agroalimentario"
      },
      {
        "Nombre": "Fondo de Emprendimiento Rural",
        "Fuente": "Corfo",
        "Fecha cierre": "2026-11-02",
        "Enlace": "https://www.corfo.cl/fondo-de-emprendimiento-rural",
        "Estado": "Abierto",
        "Monto": "USD 8,000,000",
        "Área de interés": "Desarrollo Rural",
        "Descripción": "Financiamiento para emprendimientos rurales"
      },
      {
        "Nombre": "Programa Sostenibilidad Agrícola",
        "Fuente": "Corfo",
        "Fecha cierre": "2026-09-29",
        "Enlace": "https://www.corfo.cl/programa-sostenibilidad-agrícola",
        "Estado": "Abierto",
        "Monto": "USD 12,000,000",
        "Área de interés": "Agricultura Sostenible",
        "Descripción": "Incentivos para prácticas agrícolas sostenibles"
      },
      {
        "Nombre": "Programa Jóvenes Rurales 2024",
        "Fuente": "INDAP",
        "Fecha cierre": "2026-02-28",
        "Enlace": "https://www.indap.gob.cl/programa-jóvenes-rurales-2024",
        "Estado": "Abierto",
        "Monto": "USD 20,000,000",
        "Área de interés": "Juventudes Rurales",
        "Descripción": "Apoyo integral para jóvenes rurales emprendedores"
      },
      {
        "Nombre": "Fondo de Desarrollo Rural",
        "Fuente": "INDAP",
        "Fecha cierre": "2026-02-20",
        "Enlace": "https://www.indap.gob.cl/fondo-de-desarrollo-rural",
        "Estado": "Abierto",
        "Monto": "USD 25,000,000",
        "Área de interés": "Desarrollo Rural",
        "Descripción": "Desarrollo de infraestructura rural"
      },
      {
        "Nombre": "Programa Mujeres Rurales",
        "Fuente": "INDAP",
        "Fecha cierre": "2026-03-08",
        "Enlace": "https://www.indap.gob.cl/programa-mujeres-rurales",
        "Estado": "Abierto",
        "Monto": "USD 18,000,000",
        "Área de interés": "Desarrollo Rural",
        "Descripción": "Empoderamiento de mujeres rurales"
      },
      {
        "Nombre": "Fondo de Innovación Agrícola",
        "Fuente": "FIA",
        "Fecha cierre": "2026-07-05",
        "Enlace": "https://www.fia.cl/fondo-de-innovación-agrícola",
        "Estado": "Abierto",
        "Monto": "USD 10,000,000",
        "Área de interés": "Innovación Tecnológica",
        "Descripción": "Innovación en el sector agrícola"
      },
      {
        "Nombre": "Programa SaviaLab",
        "Fuente": "FIA",
        "Fecha cierre": "2026-05-09",
        "Enlace": "https://www.fia.cl/programa-savialab",
        "Estado": "Abierto",
        "Monto": "USD 5,000,000",
        "Área de interés": "Juventudes Rurales",
        "Descripción": "Innovación temprana para jóvenes rurales"
      },
      {
        "Nombre": "Programa Seguridad Alimentaria Global",
        "Fuente": "FAO",
        "Fecha cierre": "2026-01-04",
        "Enlace": "https://www.fao.org/programa-seguridad-alimentaria-global",
        "Estado": "Abierto",
        "Monto": "USD 50,000,000",
        "Área de interés": "Seguridad Alimentaria",
        "Descripción": "Programa global de seguridad alimentaria"
      },
      {
        "Nombre": "Iniciativa Juventud Rural FAO",
        "Fuente": "FAO",
        "Fecha cierre": "2026-10-06",
        "Enlace": "https://www.fao.org/iniciativa-juventud-rural-fao",
        "Estado": "Abierto",
        "Monto": "USD 30,000,000",
        "Área de interés": "Juventudes Rurales",
        "Descripción": "Desarrollo de jóvenes rurales a nivel global"
      },
      {
        "Nombre": "Fondo Verde del Clima",
        "Fuente": "Banco Mundial",
        "Fecha cierre": "2026-09-30",
        "Enlace": "https://www.worldbank.org/fondo-verde-del-clima",
        "Estado": "Abierto",
        "Monto": "USD 100,000,000",
        "Área de interés": "Agricultura Sostenible",
        "Descripción": "Fondo para proyectos climáticos en agricultura"
      },
      {
        "Nombre": "Programa Desarrollo Rural Sostenible",
        "Fuente": "Banco Mundial",
        "Fecha cierre": "2026-06-08",
        "Enlace": "https://www.worldbank.org/programa-desarrollo-rural-sostenible",
        "Estado": "Abierto",
        "Monto": "USD 75,000,000",
        "Área de interés": "Desarrollo Rural",
        "Descripción": "Desarrollo rural sostenible en América Latina"
      },
      {
        "Nombre": "Iniciativa Agricultura Sostenible BID",
        "Fuente": "BID",
        "Fecha cierre": "2026-09-26",
        "Enlace": "https://www.iadb.org/iniciativa-agricultura-sostenible-bid",
        "Estado": "Abierto",
        "Monto": "USD 60,000,000",
        "Área de interés": "Agricultura Sostenible",
        "Descripción": "Iniciativa del BID para agricultura sostenible"
      },
      {
        "Nombre": "Programa Innovación Rural BID",
        "Fuente": "BID",
        "Fecha cierre": "2026-07-16",
        "Enlace": "https://www.iadb.org/programa-innovación-rural-bid",
        "Estado": "Abierto",
        "Monto": "USD 40,000,000",
        "Área de interés": "Innovación Tecnológica",
        "Descripción": "Innovación tecnológica en zonas rurales"
      },
      {
        "Nombre": "Programa IICA Digitalización Agroalimentaria",
        "Fuente": "IICA",
        "Fecha cierre": "2026-08-15",
        "Enlace": "https://www.iica.int/programa-iica-digitalización-agroalimentaria",
        "Estado": "Abierto",
        "Monto": "USD 25,000,000",
        "Área de interés": "Innovación Tecnológica",
        "Descripción": "Digitalización del sector agroalimentario"
      },
      {
        "Nombre": "Iniciativa IICA Cambio Climático",
        "Fuente": "IICA",
        "Fecha cierre": "2025-12-12",
        "Enlace": "https://www.iica.int/iniciativa-iica-cambio-climático",
        "Estado": "Abierto",
        "Monto": "USD 35,000,000",
        "Área de interés": "Agricultura Sostenible",
        "Descripción": "Adaptación al cambio climático en agricultura"
      }
    ]
  }
]